wfgen/WFGen.py
wfgen/WFGenModels.py
wfgen/__init__.py
wfgen-0.0.7.dist-info/METADATA
wfgen-0.0.7.dist-info/WHEEL
wfgen-0.0.7.dist-info/top_level.txt
wfgen-0.0.7.dist-info/RECORD
